{
    "tilePos": [
        {
            "x": 0.06800000369548798,
            "y": 0.0,
            "z": 0.0
        },
        {
            "x": -0.03400000184774399,
            "y": 0.0,
            "z": 0.04399999976158142
        },
        {
            "x": 0.0,
            "y": 0.0,
            "z": 0.08799999952316284
        },
        {
            "x": 0.0,
            "y": 0.0,
            "z": 0.0
        },
        {
            "x": 0.03400000184774399,
            "y": 0.0,
            "z": -0.04399999976158142
        },
        {
            "x": 0.10200000554323197,
            "y": 0.0,
            "z": 0.04399999976158142
        },
        {
            "x": -0.03400000184774399,
            "y": 0.0,
            "z": -0.04399999976158142
        },
        {
            "x": 0.03400000184774399,
            "y": 0.0,
            "z": 0.04399999976158142
        },
        {
            "x": 0.06800000369548798,
            "y": 0.0,
            "z": 0.08799999952316284
        },
        {
            "x": 0.03400000184774399,
            "y": 0.0,
            "z": 0.13199999928474427
        },
        {
            "x": -0.03400000184774399,
            "y": 0.0,
            "z": 0.13199999928474427
        },
        {
            "x": 0.10200000554323197,
            "y": 0.0,
            "z": 0.13199999928474427
        }
    ]
}